mkdocs_audio/__init__.py
mkdocs_audio/plugin.py
mkdocs_audio-0.0.2.dist-info/LICENSE
mkdocs_audio-0.0.2.dist-info/METADATA
mkdocs_audio-0.0.2.dist-info/WHEEL
mkdocs_audio-0.0.2.dist-info/entry_points.txt
mkdocs_audio-0.0.2.dist-info/top_level.txt
mkdocs_audio-0.0.2.dist-info/RECORD
