Metadata-Version: 2.1
Name: mkdocs-audio
Version: 0.0.2
Summary: MkDocs plugin to embed audio files
Home-page: https://github.com/jfcmontmorency/mkdocs-audio
Author: Jean-Francois Cartier
Author-email: jfcartier@cmontmorency.qc.ca
License: MIT
Requires-Python: >=3.6
License-File: LICENSE
Requires-Dist: mkdocs >=1.4.2
Requires-Dist: lxml >=4.7.0
